jinja2_tools/__init__.py
jinja2_tools/cli.py
jinja2_tools/exceptions.py
jinja2_tools/objects.py
jinja2_tools/util.py
jinja2_tools/validators.py
jinja2_tools/plugins/__init__.py
jinja2_tools/plugins/lookup/__init__.py
tests/__init__.py
tests/test_render.py
jinja2_tools-1.0.8.dist-info/LICENSE
jinja2_tools-1.0.8.dist-info/METADATA
jinja2_tools-1.0.8.dist-info/WHEEL
jinja2_tools-1.0.8.dist-info/entry_points.txt
jinja2_tools-1.0.8.dist-info/top_level.txt
jinja2_tools-1.0.8.dist-info/RECORD
