Metadata-Version: 2.1
Name: jinja2-tools
Version: 1.0.8
Summary: Use Jinja2 templates via cli
Home-page: https://github.com/Avielyo10/jinja2-tools.git
Author: Aviel Yosef
Author-email: Avielyo10@gmail.com
Classifier: Programming Language :: Python :: 3
Classifier: License :: OSI Approved :: GNU General Public License v3 (GPLv3)
Classifier: Operating System :: OS Independent
Requires-Python: >=3.5
License-File: LICENSE
Requires-Dist: Click
Requires-Dist: ansicolors
Requires-Dist: PyYAML
Requires-Dist: Jinja2
Requires-Dist: requests
Requires-Dist: validators
